catsyl/__init__.py
catsyl/syllogisms.py
catsyl-0.0.0.dist-info/WHEEL
catsyl-0.0.0.dist-info/entry_points.txt
catsyl-0.0.0.dist-info/METADATA
catsyl-0.0.0.dist-info/RECORD
