Metadata-Version: 2.3
Name: catsyl
Version: 0.0.0
Summary: A reference utility for categorical logic.
Author: Caleb R.
Author-email: Caleb R. <hyletic@proton.me>
Requires-Python: >=3.9
